{"name":"To validate the Equipment Report from Reports Dropdown","testSteps":[{"number":1,"description":"[1] {DB\u003dhttp://10.246.4.94/Postgres/SHAW01_SO, ID\u003d10400223}","duration":139927,"startTime":1724101268519,"result":"SUCCESS","children":[{"number":2,"description":"Given I launch http://10.246.4.94/Postgres/SHAW01_SO the Application","duration":3111,"startTime":1724101268521,"result":"SUCCESS"},{"number":3,"description":"When I enter the Credentials","duration":31033,"startTime":1724101271632,"result":"SUCCESS"},{"number":4,"description":"Given I verify the Map Section","duration":15948,"startTime":1724101302665,"result":"SUCCESS"},{"number":5,"description":"Then I Click on the reports dropdown","duration":290,"startTime":1724101318614,"result":"SUCCESS"},{"number":6,"description":"Then I Enter the 10400223 for the Entity","duration":29562,"startTime":1724101318905,"result":"SUCCESS"},{"number":7,"description":"When I validate the Title of the Entity Selected","duration":14309,"startTime":1724101348467,"result":"SUCCESS"},{"number":8,"description":"Then I Navigate to Equipment Report","duration":25907,"startTime":1724101362776,"result":"SUCCESS"},{"number":9,"description":"And I validate the Equipment Report Panel","duration":17441,"startTime":1724101388683,"result":"SUCCESS"},{"number":10,"description":"Given I Log out","duration":2322,"startTime":1724101406124,"result":"SUCCESS"}]}],"userStory":{"id":"to-validate-the-sanity-tests-for-sdk-application","storyName":"To Validate the Sanity Tests for SDK Application","path":"src/main/resources/features/Sanity_Postgres.feature","type":"feature"},"title":"To validate the Equipment Report from Reports Dropdown","description":"","tags":[{"name":"Sanity_Postgres","type":"tag"},{"name":"To Validate the Sanity Tests for SDK Application","type":"feature"}],"startTime":1724101268516,"duration":139930,"dataTable":{"headers":["DB","ID"],"rows":[{"values":["http://10.246.4.94/Postgres/SHAW01_SO","10400223"],"result":"SUCCESS"}],"predefinedRows":true,"currentRow":{"value":0},"dataSetDescriptors":[{"startRow":0,"rowCount":0,"name":"","description":""}]},"manual":false,"result":"SUCCESS"}